{
  "timestamp": "2025-08-16T09:58:30.308479",
  "test_summary": {
    "stability_testing": "Completed",
    "chaos_engineering": "Completed",
    "load_testing": "Completed",
    "security_validation": "Completed",
    "docker_health": "Completed",
    "system_monitoring": "Completed"
  },
  "reliability_metrics": {
    "stability_score": "TBD",
    "resilience_score": "TBD",
    "security_score": "TBD",
    "performance_score": "TBD",
    "overall_reliability": "TBD"
  },
  "staging_environment": {
    "ai_framework": "http://localhost:18000",
    "prometheus": "http://localhost:19093",
    "grafana": "http://localhost:13002",
    "nginx": "http://localhost:18081"
  },
  "recommendations": [
    "Review stability test results for any system weaknesses",
    "Analyze chaos engineering results for resilience improvements",
    "Validate security posture remains strong",
    "Monitor system resources for optimization opportunities",
    "Prepare for production deployment with confidence"
  ]
}